cloudheadschecker
