Metadata-Version: 2.1
Name: cloudheadschecker
Version: 0.0.4
Summary: Checks for cloud services
Home-page: https://git.aperture-labs.org/Cloudheads/cloudheadschecker
Author: Tobias Fiebig
Author-email: tobias@cloudheads.net
License: UNKNOWN
Platform: UNKNOWN
Classifier: Programming Language :: Python :: 3
Classifier: License :: OSI Approved :: GNU General Public License v3 or later (GPLv3+)
Classifier: Operating System :: OS Independent
Requires-Python: >=3.8
